[{"name":"Fruko Schulz","avg_price":4934.25,"max_price":9273,"min_price":1845},{"name":"Айва","avg_price":4740.7894736842,"max_price":8050,"min_price":504},{"name":"Батат","avg_price":4998.6,"max_price":9783,"min_price":158},{"name":"Биточки","avg_price":6580.8888888889,"max_price":9090,"min_price":248},{"name":"Блюдца","avg_price":5188.625,"max_price":8401,"min_price":2006},{"name":"Брокколи","avg_price":5464.2352941176,"max_price":9956,"min_price":949},{"name":"Брынза","avg_price":6009.05,"max_price":8626,"min_price":940},{"name":"Бурятская","avg_price":4614.8333333333,"max_price":9286,"min_price":1363},{"name":"Варенье","avg_price":4783.4736842105,"max_price":9395,"min_price":524},{"name":"Ветчина","avg_price":5014.8947368421,"max_price":9797,"min_price":575},{"name":"Гвоздика молотая","avg_price":3838.7142857143,"max_price":8338,"min_price":1332},{"name":"Говядина","avg_price":4739.0,"max_price":9603,"min_price":724},{"name":"Горох","avg_price":2344.375,"max_price":5390,"min_price":238},{"name":"Горячий шоколад","avg_price":5177.1111111111,"max_price":9362,"min_price":2046},{"name":"Грейпфрут","avg_price":4858.2,"max_price":6727,"min_price":2798},{"name":"Груша","avg_price":6882.0,"max_price":9871,"min_price":1434},{"name":"Золотое молоко","avg_price":4042.1111111111,"max_price":9867,"min_price":665},{"name":"Инжир","avg_price":4566.5555555556,"max_price":9128,"min_price":232},{"name":"Кабачок","avg_price":4568.8333333333,"max_price":9335,"min_price":568},{"name":"Каймак","avg_price":4415.5,"max_price":8248,"min_price":262},{"name":"Какао","avg_price":4448.8888888889,"max_price":9920,"min_price":397},{"name":"Капуста белокочанная","avg_price":4483.4285714286,"max_price":6923,"min_price":1205},{"name":"Каша из дробленой булгура","avg_price":4954.0909090909,"max_price":9266,"min_price":2097},{"name":"Каша из дробленой пшеницы","avg_price":5268.0,"max_price":7766,"min_price":1657},{"name":"Каша из проса","avg_price":4701.75,"max_price":8426,"min_price":1503},{"name":"Каша из теффа","avg_price":5505.3333333333,"max_price":7369,"min_price":2432},{"name":"Кашинская","avg_price":3243.6,"max_price":6205,"min_price":267},{"name":"Кетчуп","avg_price":4640.4736842105,"max_price":9674,"min_price":657},{"name":"Кефир","avg_price":6420.3333333333,"max_price":9328,"min_price":2959},{"name":"Клубника","avg_price":4763.3571428571,"max_price":9944,"min_price":655},{"name":"Кольраби","avg_price":6463.2307692308,"max_price":9923,"min_price":2577},{"name":"Косулятина","avg_price":5867.2,"max_price":9202,"min_price":489},{"name":"Крыжовник","avg_price":4687.2941176471,"max_price":9227,"min_price":661},{"name":"Лук-порей","avg_price":4368.9189189189,"max_price":9842,"min_price":245},{"name":"Мацони","avg_price":5719.0,"max_price":9599,"min_price":345},{"name":"Мороженое","avg_price":4251.8,"max_price":9367,"min_price":1377},{"name":"Морс брусничный","avg_price":4560.6875,"max_price":8554,"min_price":232},{"name":"Московская","avg_price":5390.0526315789,"max_price":9946,"min_price":665},{"name":"Моющее средство для стекол","avg_price":3729.4117647059,"max_price":8973,"min_price":224},{"name":"Мультиварка","avg_price":6965.8181818182,"max_price":9615,"min_price":2801},{"name":"Мята перечная сушеная","avg_price":4840.5833333333,"max_price":9694,"min_price":215},{"name":"Отбивная","avg_price":4669.4375,"max_price":9988,"min_price":225},{"name":"Пакеты для детских вещей","avg_price":5532.0666666667,"max_price":9889,"min_price":513},{"name":"Пакеты для животных","avg_price":4495.6,"max_price":8869,"min_price":315},{"name":"Пакеты для концерта","avg_price":4332.8571428571,"max_price":9755,"min_price":180},{"name":"Пакеты для обуви","avg_price":5280.9473684211,"max_price":9608,"min_price":211},{"name":"Пакеты для хранения одежды","avg_price":6154.1428571429,"max_price":9889,"min_price":162},{"name":"Пастернак","avg_price":5392.7142857143,"max_price":8493,"min_price":930},{"name":"Пастила","avg_price":5361.9473684211,"max_price":9916,"min_price":873},{"name":"Патиссон","avg_price":5812.6923076923,"max_price":8883,"min_price":2000},{"name":"Плавленые сырки","avg_price":8227.2857142857,"max_price":9884,"min_price":5864},{"name":"Пунш фруктовый","avg_price":4772.0526315789,"max_price":9363,"min_price":478},{"name":"Пылесос","avg_price":4574.2,"max_price":9333,"min_price":457},{"name":"Российский сыр","avg_price":6181.0,"max_price":7255,"min_price":4345},{"name":"Сангрия безалкогольная","avg_price":4338.5714285714,"max_price":8330,"min_price":1906},{"name":"Сельдерей сушеный","avg_price":4853.7894736842,"max_price":8624,"min_price":874},{"name":"Семечки (тыквенные, подсолнечника)","avg_price":5040.375,"max_price":9460,"min_price":825},{"name":"Сервелат","avg_price":4371.2727272727,"max_price":8684,"min_price":2154},{"name":"Сливки","avg_price":4194.0,"max_price":8857,"min_price":1281},{"name":"Смородина","avg_price":4245.4871794872,"max_price":9807,"min_price":147},{"name":"Сорго","avg_price":4054.5,"max_price":9255,"min_price":243},{"name":"Сосиски","avg_price":5165.2857142857,"max_price":7626,"min_price":2019},{"name":"Спрайт","avg_price":4922.1764705882,"max_price":9848,"min_price":804},{"name":"Сушеные грибы","avg_price":4646.4,"max_price":9979,"min_price":119},{"name":"Сыр","avg_price":5026.6666666667,"max_price":8216,"min_price":1718},{"name":"Тан","avg_price":4201.8333333333,"max_price":9471,"min_price":830},{"name":"Темрюкская","avg_price":5368.8571428571,"max_price":8940,"min_price":386},{"name":"Термосы","avg_price":5884.8,"max_price":9357,"min_price":2193},{"name":"Томаты в собственном соку","avg_price":4838.5789473684,"max_price":9969,"min_price":569},{"name":"Тюменская","avg_price":4260.5,"max_price":7690,"min_price":596},{"name":"Фета","avg_price":5260.2222222222,"max_price":9834,"min_price":582},{"name":"Хурма","avg_price":3349.3333333333,"max_price":5309,"min_price":103},{"name":"Челябинская","avg_price":5065.2,"max_price":7931,"min_price":892},{"name":"Черника","avg_price":4220.4545454545,"max_price":8917,"min_price":576},{"name":"Чечевица","avg_price":4540.8571428571,"max_price":9885,"min_price":602},{"name":"Шелковица","avg_price":5475.8709677419,"max_price":9914,"min_price":951},{"name":"Шпик","avg_price":6154.9,"max_price":9575,"min_price":1574},{"name":"Шумовки","avg_price":7234.3636363636,"max_price":9321,"min_price":1144},{"name":"Щавель","avg_price":6439.1428571429,"max_price":8860,"min_price":2804},{"name":"Эмменталь","avg_price":3384.6,"max_price":4868,"min_price":1311},{"name":"Яблоко","avg_price":4813.8181818182,"max_price":8874,"min_price":1133}]