<?xml version="1.0" encoding="utf-8"?>
<clothing-items>
 <clothing>
  <id>
   790856205
  </id>
  <name>
   Adidas Jeans B-1535
  </name>
  <category>
   Jeans
  </category>
  <size>
   S
  </size>
  <color>
   Синий
  </color>
  <material>
   Хлопок
  </material>
  <price>
   502016
  </price>
  <rating>
   2.07
  </rating>
  <reviews>
   870145
  </reviews>
 </clothing>
 <clothing>
  <id>
   789996702
  </id>
  <name>
   Brooks Dress Z-4907
  </name>
  <category>
   Dress
  </category>
  <size>
   XL
  </size>
  <color>
   Желтый
  </color>
  <material>
   Лен
  </material>
  <price>
   539596
  </price>
  <rating>
   4.01
  </rating>
  <reviews>
   55029
  </reviews>
  <sporty>
   no
  </sporty>
 </clothing>
 <clothing>
  <id>
   177418376
  </id>
  <name>
   Converse Shoes K-3862
  </name>
  <category>
   Shoes
  </category>
  <size>
   XL
  </size>
  <color>
   Оранжевый
  </color>
  <material>
   Вискоза
  </material>
  <price>
   510259
  </price>
  <rating>
   4.57
  </rating>
  <reviews>
   160126
  </reviews>
  <new>
   +
  </new>
  <exclusive>
   no
  </exclusive>
 </clothing>
 <clothing>
  <id>
   528251984
  </id>
  <name>
   PleinSport Belts X-9820
  </name>
  <category>
   Belts
  </category>
  <size>
   M
  </size>
  <color>
   Синий
  </color>
  <material>
   Шерсть
  </material>
  <price>
   961512
  </price>
  <rating>
   3.43
  </rating>
  <reviews>
   374387
  </reviews>
  <exclusive>
   no
  </exclusive>
  <sporty>
   yes
  </sporty>
 </clothing>
 <clothing>
  <id>
   579481967
  </id>
  <name>
   Asics Jeans L-4433
  </name>
  <category>
   Jeans
  </category>
  <size>
   L
  </size>
  <color>
   Зеленый
  </color>
  <material>
   Кожа
  </material>
  <price>
   740065
  </price>
  <rating>
   3.57
  </rating>
  <reviews>
   51643
  </reviews>
  <exclusive>
   yes
  </exclusive>
  <sporty>
   no
  </sporty>
 </clothing>
 <clothing>
  <id>
   748609594
  </id>
  <name>
   Addidas Pants C-2176
  </name>
  <category>
   Pants
  </category>
  <size>
   XL
  </size>
  <color>
   Оранжевый
  </color>
  <material>
   Лен
  </material>
  <price>
   269060
  </price>
  <rating>
   4.06
  </rating>
  <reviews>
   800018
  </reviews>
  <new>
   +
  </new>
  <sporty>
   yes
  </sporty>
 </clothing>
 <clothing>
  <id>
   542598834
  </id>
  <name>
   Under Armour Shoes X-7821
  </name>
  <category>
   Shoes
  </category>
  <size>
   XXL
  </size>
  <color>
   Синий
  </color>
  <material>
   Вискоза
  </material>
  <price>
   264954
  </price>
  <rating>
   1.4
  </rating>
  <reviews>
   655099
  </reviews>
 </clothing>
 <clothing>
  <id>
   702129119
  </id>
  <name>
   Asics Pants K-3824
  </name>
  <category>
   Pants
  </category>
  <size>
   XXL
  </size>
  <color>
   Фиолетовый
  </color>
  <material>
   Кожа
  </material>
  <price>
   136490
  </price>
  <rating>
   1.65
  </rating>
  <reviews>
   882004
  </reviews>
 </clothing>
 <clothing>
  <id>
   346677935
  </id>
  <name>
   Under Armour Skirt H-9815
  </name>
  <category>
   Skirt
  </category>
  <size>
   S
  </size>
  <color>
   Фиолетовый
  </color>
  <material>
   Кожа
  </material>
  <price>
   413102
  </price>
  <rating>
   1.29
  </rating>
  <reviews>
   406275
  </reviews>
  <exclusive>
   yes
  </exclusive>
  <sporty>
   no
  </sporty>
 </clothing>
 <clothing>
  <id>
   587230590
  </id>
  <name>
   Puma Gloves R-5009
  </name>
  <category>
   Gloves
  </category>
  <size>
   L
  </size>
  <color>
   Синий
  </color>
  <material>
   Вискоза
  </material>
  <price>
   894232
  </price>
  <rating>
   1.61
  </rating>
  <reviews>
   180771
  </reviews>
  <new>
   +
  </new>
  <exclusive>
   no
  </exclusive>
 </clothing>
 <clothing>
  <id>
   970470593
  </id>
  <name>
   Under Armour Handbags R-2413
  </name>
  <category>
   Handbags
  </category>
  <size>
   S
  </size>
  <color>
   Синий
  </color>
  <material>
   Хлопок
  </material>
  <price>
   151612
  </price>
  <rating>
   1.97
  </rating>
  <reviews>
   662344
  </reviews>
  <new>
   -
  </new>
  <exclusive>
   yes
  </exclusive>
 </clothing>
 <clothing>
  <id>
   828632950
  </id>
  <name>
   Puma Socks R-9853
  </name>
  <category>
   Socks
  </category>
  <size>
   XL
  </size>
  <color>
   Синий
  </color>
  <material>
   Нейлон
  </material>
  <price>
   901501
  </price>
  <rating>
   2.49
  </rating>
  <reviews>
   424706
  </reviews>
  <exclusive>
   yes
  </exclusive>
 </clothing>
 <clothing>
  <id>
   417776414
  </id>
  <name>
   Vans Shoes U-7505
  </name>
  <category>
   Shoes
  </category>
  <size>
   XXL
  </size>
  <color>
   Красный
  </color>
  <material>
   Вискоза
  </material>
  <price>
   151962
  </price>
  <rating>
   3.84
  </rating>
  <reviews>
   421225
  </reviews>
  <exclusive>
   no
  </exclusive>
 </clothing>
 <clothing>
  <id>
   823685882
  </id>
  <name>
   New Balance T-shirt P-5786
  </name>
  <category>
   T-shirt
  </category>
  <size>
   XL
  </size>
  <color>
   Голубой
  </color>
  <material>
   Хлопок
  </material>
  <price>
   210585
  </price>
  <rating>
   2.61
  </rating>
  <reviews>
   805570
  </reviews>
  <new>
   +
  </new>
  <exclusive>
   yes
  </exclusive>
  <sporty>
   no
  </sporty>
 </clothing>
 <clothing>
  <id>
   731884248
  </id>
  <name>
   Puma Jacket X-8263
  </name>
  <category>
   Jacket
  </category>
  <size>
   S
  </size>
  <color>
   Голубой
  </color>
  <material>
   Нейлон
  </material>
  <price>
   121580
  </price>
  <rating>
   4.89
  </rating>
  <reviews>
   216598
  </reviews>
 </clothing>
 <clothing>
  <id>
   858821543
  </id>
  <name>
   PleinSport Belts E-8667
  </name>
  <category>
   Belts
  </category>
  <size>
   XXL
  </size>
  <color>
   Зеленый
  </color>
  <material>
   Шерсть
  </material>
  <price>
   879995
  </price>
  <rating>
   4.75
  </rating>
  <reviews>
   698084
  </reviews>
  <new>
   -
  </new>
  <exclusive>
   no
  </exclusive>
  <sporty>
   no
  </sporty>
 </clothing>
 <clothing>
  <id>
   127025972
  </id>
  <name>
   Fila Skirt X-7156
  </name>
  <category>
   Skirt
  </category>
  <size>
   S
  </size>
  <color>
   Зеленый
  </color>
  <material>
   Полиэстер
  </material>
  <price>
   735732
  </price>
  <rating>
   3.88
  </rating>
  <reviews>
   798172
  </reviews>
  <exclusive>
   yes
  </exclusive>
  <sporty>
   no
  </sporty>
 </clothing>
 <clothing>
  <id>
   825938045
  </id>
  <name>
   New Balance Jacket J-3112
  </name>
  <category>
   Jacket
  </category>
  <size>
   L
  </size>
  <color>
   Голубой
  </color>
  <material>
   Хлопок
  </material>
  <price>
   329561
  </price>
  <rating>
   1.78
  </rating>
  <reviews>
   984993
  </reviews>
  <new>
   -
  </new>
  <exclusive>
   no
  </exclusive>
  <sporty>
   yes
  </sporty>
 </clothing>
 <clothing>
  <id>
   167920054
  </id>
  <name>
   Converse Handbags X-3268
  </name>
  <category>
   Handbags
  </category>
  <size>
   M
  </size>
  <color>
   Голубой
  </color>
  <material>
   Шерсть
  </material>
  <price>
   234928
  </price>
  <rating>
   3.66
  </rating>
  <reviews>
   403475
  </reviews>
  <new>
   -
  </new>
  <exclusive>
   no
  </exclusive>
  <sporty>
   no
  </sporty>
 </clothing>
 <clothing>
  <id>
   766291039
  </id>
  <name>
   Puma Shirt S-4199
  </name>
  <category>
   Shirt
  </category>
  <size>
   XL
  </size>
  <color>
   Красный
  </color>
  <material>
   Хлопок
  </material>
  <price>
   841002
  </price>
  <rating>
   2.01
  </rating>
  <reviews>
   795450
  </reviews>
  <new>
   -
  </new>
  <exclusive>
   yes
  </exclusive>
 </clothing>
 <clothing>
  <id>
   160560032
  </id>
  <name>
   Vans Shirt N-8499
  </name>
  <category>
   Shirt
  </category>
  <size>
   XL
  </size>
  <color>
   Оранжевый
  </color>
  <material>
   Кожа
  </material>
  <price>
   646433
  </price>
  <rating>
   1.57
  </rating>
  <reviews>
   322108
  </reviews>
  <sporty>
   no
  </sporty>
 </clothing>
</clothing-items>
