<?xml version="1.0" encoding="utf-8"?>
<clothing-items>
 <clothing>
  <id>
   530119302
  </id>
  <name>
   Reebok Hat T-7519
  </name>
  <category>
   Hat
  </category>
  <size>
   M
  </size>
  <color>
   Красный
  </color>
  <material>
   Шерсть
  </material>
  <price>
   774266
  </price>
  <rating>
   1.1
  </rating>
  <reviews>
   236425
  </reviews>
  <sporty>
   no
  </sporty>
 </clothing>
 <clothing>
  <id>
   341040310
  </id>
  <name>
   Lacoste Belts C-6262
  </name>
  <category>
   Belts
  </category>
  <size>
   XXL
  </size>
  <color>
   Голубой
  </color>
  <material>
   Полиэстер
  </material>
  <price>
   239313
  </price>
  <rating>
   1.69
  </rating>
  <reviews>
   830519
  </reviews>
  <sporty>
   yes
  </sporty>
 </clothing>
 <clothing>
  <id>
   716370399
  </id>
  <name>
   Ellesse Belts H-2960
  </name>
  <category>
   Belts
  </category>
  <size>
   S
  </size>
  <color>
   Желтый
  </color>
  <material>
   Шелк
  </material>
  <price>
   330889
  </price>
  <rating>
   4.22
  </rating>
  <reviews>
   848417
  </reviews>
  <new>
   -
  </new>
  <exclusive>
   yes
  </exclusive>
 </clothing>
 <clothing>
  <id>
   568131136
  </id>
  <name>
   Asics Pants H-3344
  </name>
  <category>
   Pants
  </category>
  <size>
   M
  </size>
  <color>
   Оранжевый
  </color>
  <material>
   Полиэстер
  </material>
  <price>
   414503
  </price>
  <rating>
   1.96
  </rating>
  <reviews>
   120455
  </reviews>
  <exclusive>
   yes
  </exclusive>
  <sporty>
   no
  </sporty>
 </clothing>
 <clothing>
  <id>
   808706945
  </id>
  <name>
   DC Umbrellas G-2181
  </name>
  <category>
   Umbrellas
  </category>
  <size>
   XL
  </size>
  <color>
   Фиолетовый
  </color>
  <material>
   Хлопок
  </material>
  <price>
   125117
  </price>
  <rating>
   1.14
  </rating>
  <reviews>
   586327
  </reviews>
  <exclusive>
   yes
  </exclusive>
  <sporty>
   no
  </sporty>
 </clothing>
 <clothing>
  <id>
   864368104
  </id>
  <name>
   Nike Jacket F-1903
  </name>
  <category>
   Jacket
  </category>
  <size>
   XL
  </size>
  <color>
   Фиолетовый
  </color>
  <material>
   Шерсть
  </material>
  <price>
   188585
  </price>
  <rating>
   3.99
  </rating>
  <reviews>
   539985
  </reviews>
  <new>
   -
  </new>
  <sporty>
   yes
  </sporty>
 </clothing>
 <clothing>
  <id>
   253684809
  </id>
  <name>
   Converse Belts F-6566
  </name>
  <category>
   Belts
  </category>
  <size>
   M
  </size>
  <color>
   Оранжевый
  </color>
  <material>
   Шерсть
  </material>
  <price>
   839601
  </price>
  <rating>
   2.09
  </rating>
  <reviews>
   965663
  </reviews>
  <new>
   +
  </new>
  <sporty>
   no
  </sporty>
 </clothing>
 <clothing>
  <id>
   782713180
  </id>
  <name>
   Vans Skirt S-5911
  </name>
  <category>
   Skirt
  </category>
  <size>
   XL
  </size>
  <color>
   Голубой
  </color>
  <material>
   Кожа
  </material>
  <price>
   733982
  </price>
  <rating>
   2.2
  </rating>
  <reviews>
   24882
  </reviews>
  <exclusive>
   yes
  </exclusive>
  <sporty>
   no
  </sporty>
 </clothing>
 <clothing>
  <id>
   678197971
  </id>
  <name>
   DC Sweater N-8661
  </name>
  <category>
   Sweater
  </category>
  <size>
   XL
  </size>
  <color>
   Зеленый
  </color>
  <material>
   Нейлон
  </material>
  <price>
   180562
  </price>
  <rating>
   1.56
  </rating>
  <reviews>
   756820
  </reviews>
 </clothing>
 <clothing>
  <id>
   331737591
  </id>
  <name>
   Reebok Blouse X-1868
  </name>
  <category>
   Blouse
  </category>
  <size>
   M
  </size>
  <color>
   Фиолетовый
  </color>
  <material>
   Вискоза
  </material>
  <price>
   536821
  </price>
  <rating>
   1.7
  </rating>
  <reviews>
   931292
  </reviews>
  <new>
   -
  </new>
 </clothing>
 <clothing>
  <id>
   848276565
  </id>
  <name>
   DC Jeans M-3397
  </name>
  <category>
   Jeans
  </category>
  <size>
   XXL
  </size>
  <color>
   Желтый
  </color>
  <material>
   Лен
  </material>
  <price>
   320319
  </price>
  <rating>
   1.6
  </rating>
  <reviews>
   344955
  </reviews>
  <sporty>
   no
  </sporty>
 </clothing>
 <clothing>
  <id>
   562321570
  </id>
  <name>
   Nike Shirt R-6588
  </name>
  <category>
   Shirt
  </category>
  <size>
   XL
  </size>
  <color>
   Голубой
  </color>
  <material>
   Полиэстер
  </material>
  <price>
   690935
  </price>
  <rating>
   4.03
  </rating>
  <reviews>
   131988
  </reviews>
 </clothing>
 <clothing>
  <id>
   884402740
  </id>
  <name>
   Ellesse Shoes K-3131
  </name>
  <category>
   Shoes
  </category>
  <size>
   S
  </size>
  <color>
   Фиолетовый
  </color>
  <material>
   Хлопок
  </material>
  <price>
   488833
  </price>
  <rating>
   2.43
  </rating>
  <reviews>
   500600
  </reviews>
 </clothing>
 <clothing>
  <id>
   270944347
  </id>
  <name>
   Adidas T-shirt T-6665
  </name>
  <category>
   T-shirt
  </category>
  <size>
   L
  </size>
  <color>
   Желтый
  </color>
  <material>
   Вискоза
  </material>
  <price>
   372042
  </price>
  <rating>
   1.44
  </rating>
  <reviews>
   660513
  </reviews>
  <new>
   -
  </new>
  <sporty>
   yes
  </sporty>
 </clothing>
 <clothing>
  <id>
   912670749
  </id>
  <name>
   Puma Jacket L-5467
  </name>
  <category>
   Jacket
  </category>
  <size>
   S
  </size>
  <color>
   Желтый
  </color>
  <material>
   Шелк
  </material>
  <price>
   906630
  </price>
  <rating>
   2.94
  </rating>
  <reviews>
   654207
  </reviews>
  <sporty>
   no
  </sporty>
 </clothing>
 <clothing>
  <id>
   972100103
  </id>
  <name>
   Adidas Jacket F-8010
  </name>
  <category>
   Jacket
  </category>
  <size>
   M
  </size>
  <color>
   Красный
  </color>
  <material>
   Вискоза
  </material>
  <price>
   813716
  </price>
  <rating>
   1.39
  </rating>
  <reviews>
   885465
  </reviews>
  <exclusive>
   yes
  </exclusive>
  <sporty>
   no
  </sporty>
 </clothing>
 <clothing>
  <id>
   764420959
  </id>
  <name>
   Under Armour Socks B-8084
  </name>
  <category>
   Socks
  </category>
  <size>
   XXL
  </size>
  <color>
   Желтый
  </color>
  <material>
   Вискоза
  </material>
  <price>
   372139
  </price>
  <rating>
   1.1
  </rating>
  <reviews>
   425020
  </reviews>
  <exclusive>
   no
  </exclusive>
  <sporty>
   no
  </sporty>
 </clothing>
 <clothing>
  <id>
   969472472
  </id>
  <name>
   Under Armour Blouse O-1588
  </name>
  <category>
   Blouse
  </category>
  <size>
   S
  </size>
  <color>
   Желтый
  </color>
  <material>
   Хлопок
  </material>
  <price>
   280756
  </price>
  <rating>
   4.45
  </rating>
  <reviews>
   922170
  </reviews>
  <new>
   -
  </new>
  <exclusive>
   no
  </exclusive>
 </clothing>
</clothing-items>
